check_systemd.py
check_systemd-4.1.1.dist-info/LICENSE
check_systemd-4.1.1.dist-info/METADATA
check_systemd-4.1.1.dist-info/WHEEL
check_systemd-4.1.1.dist-info/entry_points.txt
check_systemd-4.1.1.dist-info/RECORD
