Metadata-Version: 2.1
Name: check_systemd
Version: 4.1.1
Summary: Nagios / Icinga monitoring plugin to check systemd for failed units.
Home-page: https://github.com/Josef-Friedrich/check_systemd
License: LGPL-2.1-only
Author: Josef Friedrich
Author-email: josef@friedrich.rocks
Requires-Python: >=3.8,<4.0
Classifier: Development Status :: 5 - Production/Stable
Classifier: Environment :: Plugins
Classifier: Intended Audience :: System Administrators
Classifier: License :: OSI Approved
Classifier: License :: OSI Approved :: GNU Lesser General Public License v2 (LGPLv2)
Classifier: Operating System :: POSIX :: Linux
Classifier: Programming Language :: Python
Classifier: Programming Language :: Python :: 3
Classifier: Programming Language :: Python :: 3.8
Classifier: Programming Language :: Python :: 3.9
Classifier: Programming Language :: Python :: 3.10
Classifier: Programming Language :: Python :: 3.11
Classifier: Programming Language :: Python :: 3.12
Classifier: Programming Language :: Python :: 3.13
Classifier: Topic :: System :: Networking :: Monitoring
Requires-Dist: nagiosplugin (>=1.2,<2.0)
Project-URL: Repository, https://github.com/Josef-Friedrich/check_systemd
